{"trial_id": "0aea8ba5940beae28f40f239b52cf8f9", "hyperparameters": {"space": [{"class_name": "Int", "config": {"name": "units", "default": null, "conditions": [], "min_value": 32, "max_value": 512, "step": 32, "sampling": null}}, {"class_name": "Choice", "config": {"name": "reg_lambda", "default": 0.001, "conditions": [], "values": [0.001, 0.005, 0.01, 0.02, 0.05], "ordered": true}}, {"class_name": "Choice", "config": {"name": "learning_rate", "default": 0.01, "conditions": [], "values": [0.01, 0.001, 0.0001], "ordered": true}}], "values": {"units": 160, "reg_lambda": 0.005, "learning_rate": 0.001, "tuner/epochs": 2, "tuner/initial_epoch": 0, "tuner/bracket": 3, "tuner/round": 0}}, "metrics": {"metrics": {"loss": {"direction": "min", "observations": [{"value": [3.881124258041382], "step": 0}]}, "categorical_accuracy": {"direction": "max", "observations": [{"value": [0.21875], "step": 0}]}, "val_loss": {"direction": "min", "observations": [{"value": [3.3095948696136475], "step": 0}]}, "val_categorical_accuracy": {"direction": "max", "observations": [{"value": [0.28125], "step": 0}]}}}, "score": 0.28125, "best_step": 0, "status": "COMPLETED"}